rimdev_lib
