Metadata-Version: 2.1
Name: rimdev-lib
Version: 0.0.14
Summary: Librería personal para desarrollo de aplicaciones
Home-page: https://github.com/Faroock/py-rimlib
Author: Faroock
Author-email: faroock@gmail.com
License: MIT License
Download-URL: https://github.com/Faroock/py-rimlib/tarball/v0.0.14
Keywords: faroock,rim,rimdev,rimlib,rimdev_lib
Platform: UNKNOWN
License-File: LICENSE
